{
    "information": {
        "fullname": "KLOOK\u5ba2\u8def",
        "code_name": "klook",
        "external_link": "https://www.klook.com/zh-TW/event/city-mcate/19-3-taipei-convention-exhibition-tickets/"
    },
    "counts": 52,
    "last_update": "2024-04-01T00:53:46.129512+00:00",
    "data": [
        {
            "systematics": "klook",
            "title": "\u7b2c29\u5c46\u53f0\u5317\u570b\u969b\u512a\u826f\u5bb6\u5177\u66a8\u5bb6\u8a2d\u8a08\u7528\u54c1\u5c55",
            "date": "5\u67083\u65e5(\u9031\u4e94) - 5\u67086\u65e5(\u9031\u4e00)",
            "address": "-",
            "source_url": "https://www.klook.com/zh-TW/event-detail/101023868-2024-furniture-exhibition/",
            "UUID": "b5292c306e405eb884800ee29e92ce1f",
            "figure": "https://i.imgur.com/JQ4isKp.webp"
        },
        {
            "systematics": "klook",
            "title": "\u84bc\u84bc\uff1a\u690d\u7269\u7cfb\u7f8e\u5c55 - \u591a\u7d0d\u85dd\u8853\u83ef\u5c71\u9928",
            "date": "3\u670827\u65e5(\u9031\u4e09) - 5\u670812\u65e5(\u9031\u65e5)",
            "address": "\u83ef\u5c71\u6587\u5275",
            "source_url": "https://www.klook.com/zh-TW/event-detail/101023855-2024-botanical-art-exhibition/",
            "UUID": "781a7ff728125f97bea93ce7c2456605",
            "figure": "https://i.imgur.com/vTEt2j7.webp"
        },
        {
            "systematics": "klook",
            "title": "Y.E.S. TAIWAN X",
            "date": "4\u67086\u65e5(\u9031\u516d) - 4\u670827\u65e5(\u9031\u516d)",
            "address": "-",
            "source_url": "https://www.klook.com/zh-TW/event-detail/101023854-2024-yes-taiwan-exhibition/",
            "UUID": "986b983323c054938bb8f19eebf0e88c",
            "figure": "https://i.imgur.com/0YqPjb4.webp"
        },
        {
            "systematics": "klook",
            "title": "2024\u53f0\u5317\u570b\u969b\u7cbe\u7dfb\u9152\u5c55",
            "date": "8\u670816\u65e5(\u9031\u4e94) - 8\u670819\u65e5(\u9031\u4e00)",
            "address": "-",
            "source_url": "https://www.klook.com/zh-TW/event-detail/101023847-2024-taipei-fine-wine-eexpo/",
            "UUID": "d6fe6ef9fdb7522bb35dd22fcca5769e",
            "figure": "https://i.imgur.com/QOjAx2o.webp"
        },
        {
            "systematics": "klook",
            "title": "2024\u53f0\u5317\u8a2d\u8a08\u73a9\u5275\u610f\u5c55",
            "date": "6\u670828\u65e5(\u9031\u4e94) - 7\u67081\u65e5(\u9031\u4e00)",
            "address": "-",
            "source_url": "https://www.klook.com/zh-TW/event-detail/101023841-2024-design-exhibition/",
            "UUID": "6a24af7ca23554e7819a684a4748dfc6",
            "figure": "https://i.imgur.com/4OOd8Vs.webp"
        },
        {
            "systematics": "klook",
            "title": "2024\u53f0\u5317\u570b\u969b\u5275\u610f\u6587\u5177\u5c55",
            "date": "6\u670828\u65e5(\u9031\u4e94) - 7\u67081\u65e5(\u9031\u4e00)",
            "address": "-",
            "source_url": "https://www.klook.com/zh-TW/event-detail/101023839-2024-taiwan-stationary-fair/",
            "UUID": "2536680ed40556f098a2df2e2b77d127",
            "figure": "https://i.imgur.com/utnn1eB.webp"
        },
        {
            "systematics": "klook",
            "title": "\u7b2c22\u5c46\u53f0\u5317\u570b\u969b\u6578\u4f4d\u5f71\u97f3\u5bb6\u96fb\u5c55",
            "date": "6\u670828\u65e5(\u9031\u4e94) - 7\u67081\u65e5(\u9031\u4e00)",
            "address": "-",
            "source_url": "https://www.klook.com/zh-TW/event-detail/101023728-2024-taipei-future-technology/",
            "UUID": "8468dc0609d85f5888e7d2dc51722899",
            "figure": "https://i.imgur.com/Str0Wog.webp"
        },
        {
            "systematics": "klook",
            "title": "\u4e09\u79e6\u516c\u5b6b \u5f35\u514b\u6649\u7532\u8fb0\u66f8\u756b\u5c55",
            "date": "4\u670816\u65e5(\u9031\u4e8c) - 4\u670830\u65e5(\u9031\u4e8c)",
            "address": "-",
            "source_url": "https://www.klook.com/zh-TW/event-detail/101023803-2024-calligraphy-exhibition/",
            "UUID": "4fff84f250565c8397e2a6c5046b5759",
            "figure": "https://i.imgur.com/MMibuSL.webp"
        },
        {
            "systematics": "klook",
            "title": "2024 \u7b2c\u5341\u4e5d\u5c46\u53f0\u7063\u7926\u7269\u5c55",
            "date": "5\u67084\u65e5(\u9031\u516d)",
            "address": "-",
            "source_url": "https://www.klook.com/zh-TW/event-detail/101023787-2024-taiwan-mineral-show/",
            "UUID": "d581352442b85cfaa25cad84fab2e4d8",
            "figure": "https://i.imgur.com/re3jRoK.webp"
        },
        {
            "systematics": "klook",
            "title": "\u5fe0\u6cf0\u7f8e\u8853\u9928\u300a\u6587\u660e\uff1a\u7576\u4ee3\u751f\u6d3b\u555f\u793a\u9304 Civilization: The Way We Live Now\u300b",
            "date": "5\u670818\u65e5(\u9031\u516d) - 6\u670830\u65e5(\u9031\u65e5)",
            "address": "-",
            "source_url": "https://www.klook.com/zh-TW/activity/110662-civilization-the-way-we-live-now/",
            "UUID": "10ca5e9b00fc57a7a6761b05f206c535",
            "figure": "-"
        },
        {
            "systematics": "klook",
            "title": "\u53b2\u9670\u5b85\u4e4b\u65c5 \u6c89\u6d78\u5f0f\u9ad4\u9a57\u5c55",
            "date": "4\u67081\u65e5(\u9031\u4e00) - 4\u67087\u65e5(\u9031\u65e5)",
            "address": "-",
            "source_url": "https://www.klook.com/zh-TW/activity/100341-the-conjuring-immersive-exhibition/",
            "UUID": "df052ea872f65633a2cdd2ffc3bdf2a2",
            "figure": "-"
        },
        {
            "systematics": "klook",
            "title": "\u5e7e\u4f55\u8b8a\u594f - \u6731\u70ba\u767d x \u6cd5\u8cc8\u5e0c\u8fea x \u97d3\u8fea\u6b50",
            "date": "3\u67089\u65e5(\u9031\u516d) - 4\u670828\u65e5(\u9031\u65e5)",
            "address": "\u5c55\u89bd",
            "source_url": "https://www.klook.com/zh-TW/event-detail/101023727-2024-geometric-variations/",
            "UUID": "5caee4a385205c8e89af6065f39dab02",
            "figure": "-"
        },
        {
            "systematics": "klook",
            "title": "\u6731\u9298\u2014\u767d\u5f69\u4eba\u9593",
            "date": "3\u67088\u65e5(\u9031\u4e94) - 4\u670828\u65e5(\u9031\u65e5)",
            "address": "\u4e9e\u6d32\u85dd\u8853\u4e2d\u5fc3",
            "source_url": "https://www.klook.com/zh-TW/event-detail/101023708-2024-ju-ming-exhibtiion/",
            "UUID": "52703b9e21b95c2abacdb23e3e65e1b8",
            "figure": "-"
        },
        {
            "systematics": "klook",
            "title": "\u6df5\u85ea - \u30db\u30ce\u30b8\u30ed\u30c8\u30f2\u30b8\u53f0\u7063\u521d\u500b\u5c55",
            "date": "4\u67086\u65e5(\u9031\u516d) - 5\u67085\u65e5(\u9031\u65e5)",
            "address": "-",
            "source_url": "https://www.klook.com/zh-TW/event-detail/101023703-2024-honojiro-towoji/",
            "UUID": "b87c541829f655efa995e1e765d34b57",
            "figure": "-"
        },
        {
            "systematics": "klook",
            "title": "\u7a1c\u93e1\u2014\u6642\u5149\u4e4b\u85cd - \u6df1\u4e95\u9686\u500b\u5c55",
            "date": "3\u670816\u65e5(\u9031\u516d) - 4\u670828\u65e5(\u9031\u65e5)",
            "address": "-",
            "source_url": "https://www.klook.com/zh-TW/event-detail/101023702-2024-prism-time-in-blue/",
            "UUID": "1e212b9e133856fc9e608188afbe9f8c",
            "figure": "-"
        },
        {
            "systematics": "klook",
            "title": "MoCA Video\u300c\u5c45\u5bb6\u7b26\u865f\u5b78\u300d",
            "date": "3\u670823\u65e5(\u9031\u516d) - 5\u67085\u65e5(\u9031\u65e5)",
            "address": "-",
            "source_url": "https://www.klook.com/zh-TW/event-detail/101023699-2024-semiotics-of-the-home/",
            "UUID": "8326771b1379575ea25cfe0c1f16211a",
            "figure": "-"
        },
        {
            "systematics": "klook",
            "title": "\u9b3c\u9b42\u8207\u6df1\u85cd\u6d77\uff1a\u81f4\u7a4e\u500b\u5c55 - \u7b2c\u4e03\u5c46\u9285\u9418\u85dd\u8853\u8cde",
            "date": "3\u670830\u65e5(\u9031\u516d) - 5\u670812\u65e5(\u9031\u65e5)",
            "address": "-",
            "source_url": "https://www.klook.com/zh-TW/event-detail/101023683-2024-ghost-sea-exhibition/",
            "UUID": "3a39c019553a577fa7da904058b9ebff",
            "figure": "-"
        },
        {
            "systematics": "klook",
            "title": "\u6e67\u73fe SYNERGY - \u85a9\u74a8\u5982 Cynthia Sah x \u5c3c\u53e4\u62c9\uff0e\u8c9d\u675c Nicolas Bertoux \u96d9\u500b\u5c55",
            "date": "4\u670813\u65e5(\u9031\u516d) - 5\u670825\u65e5(\u9031\u516d)",
            "address": "-",
            "source_url": "https://www.klook.com/zh-TW/event-detail/101023670-2024-synergy-exhibition/",
            "UUID": "ef46d1b090f85b1da901d3fc56807ef0",
            "figure": "-"
        },
        {
            "systematics": "klook",
            "title": "HYBE\u651d\u5f71\u5c55 - [HYBE INSIGHT] The Daydream Believers: \uafc8, \ub9c8\uce68\ub0b4 in Taipei",
            "date": "3\u670822\u65e5(\u9031\u4e94) - 4\u670828\u65e5(\u9031\u65e5)",
            "address": "-",
            "source_url": "https://www.klook.com/zh-TW/event-detail/101023635-2024-hybe-insight-exhibition/",
            "UUID": "d286507025c65eacb556d7d6d24f9ede",
            "figure": "-"
        },
        {
            "systematics": "klook",
            "title": "\u5fae\u5fae\u986b\u52d5\u4e4b\u9593 Between Slight Tremors - \u9673\u5349\u7a4e\u500b\u5c55",
            "date": "3\u670822\u65e5(\u9031\u4e94) - 5\u670811\u65e5(\u9031\u516d)",
            "address": "-",
            "source_url": "https://www.klook.com/zh-TW/event-detail/101023573-2024-between-slight-tremors/",
            "UUID": "b661f8b20fa35fa496e112e0361e41d0",
            "figure": "-"
        },
        {
            "systematics": "klook",
            "title": "\u6797\u7f8e\u96c5\u8336\u5668\u5c55",
            "date": "4\u67082\u65e5(\u9031\u4e8c) - 4\u670814\u65e5(\u9031\u65e5)",
            "address": "-",
            "source_url": "https://www.klook.com/zh-TW/event-detail/101023559-2024-tea-equipment-exhibition/",
            "UUID": "c0e865389e0952cf9fd1b174eb4d60fa",
            "figure": "-"
        },
        {
            "systematics": "klook",
            "title": "\u591c\u5922 - 2024 \u5bf6\u85cf\u5dd6\u5149\u7bc0",
            "date": "3\u670823\u65e5(\u9031\u516d) - 5\u67085\u65e5(\u9031\u65e5)",
            "address": "\u5bf6\u85cf\u5dd6\u570b\u969b\u85dd\u8853\u6751",
            "source_url": "https://www.klook.com/zh-TW/event-detail/101023540-2024-treasure-hill-light-fest/",
            "UUID": "70a800fb9e365cbdb0ad9f77b5c9b9f8",
            "figure": "-"
        },
        {
            "systematics": "klook",
            "title": "\u4e00\u62cd\u5373\u5f71\uff1a\u62cd\u7acb\u5f97\u570b\u969b\u540d\u5bb6\u651d\u5f71\u5927\u5c55 - \u5e2b\u5927\u7f8e\u8853\u9928",
            "date": "3\u67089\u65e5(\u9031\u516d) - 6\u67087\u65e5(\u9031\u4e94)",
            "address": "-",
            "source_url": "https://www.klook.com/zh-TW/event-detail/101023521-2024-the-polaroid-project/",
            "UUID": "d8ab734e5004517f9f9603f647314528",
            "figure": "-"
        },
        {
            "systematics": "klook",
            "title": "\u95dc\u65bc\u4eba\u7684\u4e00\u5834\u8a66\u93e1\u5be6\u9a57 - \u9673\u5cb3\u5b8f\u5275\u4f5c\u500b\u5c55",
            "date": "3\u67089\u65e5(\u9031\u516d) - 4\u67083\u65e5(\u9031\u4e09)",
            "address": "-",
            "source_url": "https://www.klook.com/zh-TW/event-detail/101023516-2024-chen-yue-hung-exhibition/",
            "UUID": "2994b4d126d65cf28f86b606db8e3983",
            "figure": "-"
        },
        {
            "systematics": "klook",
            "title": "\u7559\u7d66\u5927\u5730\u66f4\u591a\u8272\u5f69 - \u512a\u5e2d\u592b\u7279\u5c55",
            "date": "3\u67082\u65e5(\u9031\u516d) - 4\u670828\u65e5(\u9031\u65e5)",
            "address": "-",
            "source_url": "https://www.klook.com/zh-TW/event-detail/101023425-2024-yosifu-taipei-exhibition/",
            "UUID": "c8c638b5d9b05fdf94a2d81c1a1b6910",
            "figure": "https://i.imgur.com/Aj6wX2l.webp"
        },
        {
            "systematics": "klook",
            "title": "\u89c0\u5bdf\u4e4b\u6a39\u50a2\u4ff1\u2014\u50a2\u4ff1\uff0c\u5bb6\u5ead\u7684\u4e00\u4efd\u5b50 2024",
            "date": "3\u670822\u65e5(\u9031\u4e94) - 4\u670815\u65e5(\u9031\u4e00)",
            "address": "-",
            "source_url": "https://www.klook.com/zh-TW/event-detail/101023448-2024-upright-exhibition/",
            "UUID": "00fe63e24f01527fb6521685c07b46f3",
            "figure": "https://i.imgur.com/8CL5WtC.webp"
        },
        {
            "systematics": "klook",
            "title": "\u4eba\u4f9b\u667a\u6167\uff1a\u6709\u8840\u6709\u8089\u6709\u5275\u610f\ufe31\u8f14\u5927\u5ee3\u544a\u50b3\u64ad\u5b78\u7cfb 27 \u5c46\u7562\u696d\u5c55\u89bd\ufe31\u677e\u5c71\u6587\u5275\u5712\u5340",
            "date": "4\u670812\u65e5(\u9031\u4e94) - 4\u670814\u65e5(\u9031\u65e5)",
            "address": "-",
            "source_url": "https://www.klook.com/zh-TW/event-detail/101023421-2024-fjuad27-exhibition/",
            "UUID": "aba93a9aa57b5dba832cedbee1dc962d",
            "figure": "https://i.imgur.com/Axhhgl3.webp"
        },
        {
            "systematics": "klook",
            "title": "\u85cf\u85dd\u65bc\u5ba4 - \u5e38\u7389\u9650\u91cf\u7248\u756b\u7279\u5c55",
            "date": "3\u67084\u65e5(\u9031\u4e00) - 5\u67084\u65e5(\u9031\u516d)",
            "address": "-",
            "source_url": "https://www.klook.com/zh-TW/event-detail/101023418-2024-san-yu-exhibition/",
            "UUID": "941ed0b270a757e491dcecfb392dc940",
            "figure": "https://i.imgur.com/SnWWpeM.webp"
        },
        {
            "systematics": "klook",
            "title": "\u5e7b\u6ba4\u2500\u63d0\u6469\u7279\u65af\uff0e\u5b89\u683c\u842c\uff0e\u5eab\u65af\u8afe\u500b\u5c55",
            "date": "2\u670824\u65e5(\u9031\u516d) - 4\u670821\u65e5(\u9031\u65e5)",
            "address": "-",
            "source_url": "https://www.klook.com/zh-TW/event-detail/101023363-2024-phantoms-exhibition/",
            "UUID": "5405bfeedaa95d53ae5ca91db16b55bf",
            "figure": "https://i.imgur.com/C7kj3vr.webp"
        },
        {
            "systematics": "klook",
            "title": "\u5317\u6295\u8907\u5beb\u672c Beitou Palimpsest",
            "date": "2\u670824\u65e5(\u9031\u516d) - 4\u670814\u65e5(\u9031\u65e5)",
            "address": "-",
            "source_url": "https://www.klook.com/zh-TW/event-detail/101023110-2024-beitou-palimpsest/",
            "UUID": "db05b8fdadcb5894a4a906e3738c5698",
            "figure": "https://i.imgur.com/j9abXKA.webp"
        },
        {
            "systematics": "klook",
            "title": "\u7389\u8fb0\u5927\u8c61 - \u5875\u4e09\u500b\u5c55",
            "date": "3\u67089\u65e5(\u9031\u516d) - 4\u670825\u65e5(\u9031\u56db)",
            "address": "-",
            "source_url": "https://www.klook.com/zh-TW/event-detail/101023104-2024-chen-san-solo-exhibition/",
            "UUID": "818179c12ee3510e8ba2567e396fe53d",
            "figure": "https://i.imgur.com/3rB9l1h.webp"
        },
        {
            "systematics": "klook",
            "title": "2024\u53f0\u5317\u97f3\u97ff\u535a\u89bd\u6703 - \u53f0\u5317\u4e16\u8cbf\u4e00\u9928",
            "date": "3\u670829\u65e5(\u9031\u4e94) - 4\u67081\u65e5(\u9031\u4e00)",
            "address": "-",
            "source_url": "https://www.klook.com/zh-TW/event-detail/101023058-2024-taipei-audio-expo/",
            "UUID": "d5fd1d792bfa5d22b7c5097e2010b073",
            "figure": "https://i.imgur.com/n0wz4TY.webp"
        },
        {
            "systematics": "klook",
            "title": "2024 \u7b2c34\u5c46\u53f0\u5317\u96fb\u5668\u7a7a\u8abf\u5f71\u97f33C\u5927\u5c55 - \u53f0\u5317\u4e16\u8cbf\u4e00\u9928",
            "date": "3\u670829\u65e5(\u9031\u4e94) - 4\u67081\u65e5(\u9031\u4e00)",
            "address": "-",
            "source_url": "https://www.klook.com/zh-TW/event-detail/101023054-2024-electrical-appliance-expo/",
            "UUID": "3bd788df1f3453c892aac65e6147a429",
            "figure": "https://i.imgur.com/fG5DOv4.webp"
        },
        {
            "systematics": "klook",
            "title": "\u4e00\u5e74\u8a08\u5283\uff1a\u300c\u5ddd\u5802\u300d",
            "date": "2024\u5e741\u670827\u65e5(\u9031\u516d) - 2025\u5e741\u67085\u65e5(\u9031\u65e5)",
            "address": "-",
            "source_url": "https://www.klook.com/zh-TW/event-detail/101022906-2024-outing-exhibition/",
            "UUID": "e229db2f09a55307b2f2f64f09c7b6b8",
            "figure": "-"
        },
        {
            "systematics": "klook",
            "title": "\u4f60\u597d\uff0c\u4eba\u985e\uff01Hello, Human!",
            "date": "1\u670827\u65e5(\u9031\u516d) - 5\u670812\u65e5(\u9031\u65e5)",
            "address": "-",
            "source_url": "https://www.klook.com/zh-TW/event-detail/101022905-2024-hello-human/",
            "UUID": "4bd37b096eb75f6a82bfb457fb4a195b",
            "figure": "-"
        },
        {
            "systematics": "klook",
            "title": "\u3010\u7dda\u4e0a\u7248\u3011\u81fa\u5357\u5e02\u7f8e\u8853\u9928\u300c\u5357\u85b0\u85dd\u97fb\uff0d\u9673\u6f84\u6ce2\u3001\u90ed\u67cf\u5ddd\u3001\u8a31\u6b66\u52c7\u3001\u6c88\u54f2\u54c9\u85dd\u8853\u5bb6\u5c08\u5ba4\u300d\u7dda\u4e0a\u5c55\u89bd",
            "date": "2024\u5e744\u67081\u65e5(\u9031\u4e00) - 2025\u5e741\u670818\u65e5(\u9031\u516d)",
            "address": "-",
            "source_url": "https://www.klook.com/zh-TW/activity/103571-paintings-in-the-southern-breeze-online-exhibition/",
            "UUID": "5565769bff1052c1af370f0e957c73c8",
            "figure": "-"
        },
        {
            "systematics": "klook",
            "title": "\u3010\u7dda\u4e0a\u7248\u3011\u5370\u8c61\u30fb\u7d93\u5178\u2014\u5370\u8c61\u6d3e 150 \u9031\u5e74\u7dda\u4e0a\u5c55\u89bd",
            "date": "4\u67081\u65e5(\u9031\u4e00) - 12\u670826\u65e5(\u9031\u56db)",
            "address": "-",
            "source_url": "https://www.klook.com/zh-TW/activity/103468-online-immersive-art-exhibition-impressionism/",
            "UUID": "1fd3432c192a5b5d81be282150935f90",
            "figure": "-"
        },
        {
            "systematics": "klook",
            "title": "\u66fe\u5728\u7684\u5f62\u8de1 - \u674e\u608c\u6b3d x \u90b1\u5fb7\u96f2\u651d\u5f71\u6350\u8d08\u5c55",
            "date": "2023\u5e7412\u67087\u65e5(\u9031\u56db) - 2024\u5e744\u670828\u65e5(\u9031\u65e5)",
            "address": "\u570b\u5bb6\u651d\u5f71\u6587\u5316\u4e2d\u5fc3",
            "source_url": "https://www.klook.com/zh-TW/event-detail/101021941-2023-traces-of-disappearing/",
            "UUID": "a7ccd22b1a5d5ea1bc37d56120ade4cd",
            "figure": "-"
        },
        {
            "systematics": "klook",
            "title": "Got RIFF \u7576\u4ee3\u5e03\u888b\u6232\u7279\u5c55 - \u53f0\u5317\u5076\u6232\u9928",
            "date": "2023\u5e7412\u67088\u65e5(\u9031\u4e94) - 2024\u5e746\u670830\u65e5(\u9031\u65e5)",
            "address": "-",
            "source_url": "https://www.klook.com/zh-TW/event-detail/101021893-2024-got-riff-exhibition/",
            "UUID": "7077b8be079955e6b723428bf46774e3",
            "figure": "-"
        },
        {
            "systematics": "klook",
            "title": "\u6210\u70ba\u4eba\u4ee5\u5916\u7684 - \u81fa\u7063\u52d5\u7269\u6587\u5b78\u7279\u5c55",
            "date": "2023\u5e7410\u670827\u65e5(\u9031\u4e94) - 2024\u5e744\u670828\u65e5(\u9031\u65e5)",
            "address": "\u81fa\u7063\u6587\u5b78\u57fa\u5730",
            "source_url": "https://www.klook.com/zh-TW/event-detail/101021469-2023-animals-taiwan-literature/",
            "UUID": "c6d2c382d7985386b7f467c3539b8b9e",
            "figure": "-"
        },
        {
            "systematics": "klook",
            "title": "\u7c89\u7d05\u8c6c\u5c0f\u59b9\u91ce\u9910\u8da3\u4e92\u52d5\u7279\u5c55",
            "date": "4\u67081\u65e5(\u9031\u4e00) - 4\u67087\u65e5(\u9031\u65e5)",
            "address": "-",
            "source_url": "https://www.klook.com/zh-TW/activity/100574-peppa-pig-picnic-fun/",
            "UUID": "dd47db59082f5562bcab914c8fc35d8f",
            "figure": "-"
        },
        {
            "systematics": "klook",
            "title": "\u7269\u601d\u4eba\uff1a\u4ee5\u7269\u4ef6\u8207\u539f\u9109\u8a18\u61b6\u95b1\u8b80\u7576\u4ee3\u53f0\u5317\u5ba2\u5bb6 - \u5ba2\u5bb6\u6587\u5316\u4e3b\u984c\u5c55",
            "date": "2023\u5e749\u670822\u65e5(\u9031\u4e94) - 2024\u5e744\u670830\u65e5(\u9031\u4e8c)",
            "address": "\u81fa\u5317\u5e02\u5ba2\u5bb6\u6587\u5316\u4e3b\u984c\u516c\u5712",
            "source_url": "https://www.klook.com/zh-TW/event-detail/101021304-2023-objects-remind-of-you/",
            "UUID": "8619aad1a44e52058243aae4669e648d",
            "figure": "-"
        },
        {
            "systematics": "klook",
            "title": "\u6211\u662f\u9738\u738b\u9f8d20\u9031\u5e74\u5c55-\u6b61\u8fce\u5149\u81e8\u5bae\u897f\u9054\u4e5f\u904a\u6a02\u5712",
            "date": "4\u67081\u65e5(\u9031\u4e00) - 4\u67087\u65e5(\u9031\u65e5)",
            "address": "-",
            "source_url": "https://www.klook.com/zh-TW/activity/99386-i-am-a-tyrannosaurus/",
            "UUID": "4f7ffd90830251f2b45b466f7e548142",
            "figure": "-"
        },
        {
            "systematics": "klook",
            "title": "HELLO KITTY 50\u9031\u5e74\u7279\u5c55\uff1a\u8207\u672a\u4f86\u505a\u670b\u53cb\u5427\uff01",
            "date": "4\u67081\u65e5(\u9031\u4e00) - 4\u67087\u65e5(\u9031\u65e5)",
            "address": "-",
            "source_url": "https://www.klook.com/zh-TW/activity/98512-hello-kitty-50th-anniversay/",
            "UUID": "c63ece0f6b4b55f6a4bcd95d7939153a",
            "figure": "-"
        },
        {
            "systematics": "klook",
            "title": "\u4f8f\u7f85\u7d00X\u6050\u9f8d\u96ea\u4e16\u754c\u53f0\u5317\u7ad9",
            "date": "2023\u5e7412\u670829\u65e5(\u9031\u4e94) - 2024\u5e744\u67087\u65e5(\u9031\u65e5)",
            "address": "\u5317\u85dd\u4e2d\u5fc3",
            "source_url": "https://www.klook.com/zh-TW/event-detail/101020871-2023-jurassic-exhibition-taipe/",
            "UUID": "97000d32b28358f090dde0d914a7cf1e",
            "figure": "-"
        },
        {
            "systematics": "klook",
            "title": "\u5370\u8c61\u6d3e150\u9031\u5e74\u5149\u5f71\u85dd\u8853\u5c55",
            "date": "4\u67081\u65e5(\u9031\u4e00) - 4\u67087\u65e5(\u9031\u65e5)",
            "address": "-",
            "source_url": "https://www.klook.com/zh-TW/activity/98447-immersive-art-exhibition-immressionism/",
            "UUID": "bf5e925ba811586fb7797727223e1332",
            "figure": "-"
        },
        {
            "systematics": "klook",
            "title": "\u5947\u5e7b\u52d5\u7269\u68ee\u6797 \u6a0b\u53e3\u88d5\u5b50\u5c55",
            "date": "4\u67081\u65e5(\u9031\u4e00) - 4\u67087\u65e5(\u9031\u65e5)",
            "address": "-",
            "source_url": "https://www.klook.com/zh-TW/activity/96738-fantasy-animal-forest-higuchi-yuko/",
            "UUID": "290127802d47567abae36a782fc28d7d",
            "figure": "-"
        },
        {
            "systematics": "klook",
            "title": "THE \u54c6\u5566A\u5922\u5c55 \u53f0\u5317 2023",
            "date": "4\u67081\u65e5(\u9031\u4e00) - 4\u67087\u65e5(\u9031\u65e5)",
            "address": "-",
            "source_url": "https://www.klook.com/zh-TW/activity/96105-the-doraemon-taipei-2023/",
            "UUID": "2525257a1bf85e8c9358b3ed5509ba06",
            "figure": "-"
        },
        {
            "systematics": "klook",
            "title": "\u5947\u5e7b\u52d5\u7269\u68ee\u6797 \u6a0b\u53e3\u88d5\u5b50\u5c55 - \u6a0b\u53e3\u88d5\u5b50\u9996\u6b21\u6d77\u5916\u5927\u578b\u500b\u5c55",
            "date": "2023\u5e7412\u670830\u65e5(\u9031\u516d) - 2024\u5e744\u67087\u65e5(\u9031\u65e5)",
            "address": "\u4e2d\u6b63\u7d00\u5ff5\u5802",
            "source_url": "https://www.klook.com/zh-TW/event-detail/101019689-2023-higuchiyukoten-taipei/",
            "UUID": "a97e6c06b38f5b80b96289670f6a43cd",
            "figure": "https://i.imgur.com/1tZTZAP.webp"
        },
        {
            "systematics": "klook",
            "title": "\u5bd3\u610f\u6240\u5728 - \u738b\u4ec1\u5091 x \u9ece\u5fd7\u6587\u5c0d\u8a71\u5c55",
            "date": "2023\u5e748\u670815\u65e5(\u9031\u4e8c) - 2024\u5e744\u670830\u65e5(\u9031\u4e8c)",
            "address": "-",
            "source_url": "https://www.klook.com/zh-TW/event-detail/101019053-2023-the-where-we-are/",
            "UUID": "729d0764c47758618cb199a19ea1b465",
            "figure": "https://i.imgur.com/QcB8CTj.webp"
        },
        {
            "systematics": "klook",
            "title": "\u8de8\u2027\u4ea4\u2027\u901a\uff1a\u5f9e\u300c\u5927\u962a\u5546\u8239\u682a\u5f0f\u6703\u793e\u81fa\u5317\u652f\u5e97\u300d\u5230\u300c\u570b\u5bb6\u651d\u5f71\u6587\u5316\u4e2d\u5fc3\u81fa\u5317\u9928\u300d - \u5e38\u8a2d\u5c55\u51fa",
            "date": "2021\u5e743\u670825\u65e5(\u9031\u56db) - 2024\u5e7412\u670831\u65e5(\u9031\u4e8c)",
            "address": "\u570b\u5bb6\u651d\u5f71\u6587\u5316\u4e2d\u5fc3",
            "source_url": "https://www.klook.com/zh-TW/event-detail/101009551-2022-trans-communication/",
            "UUID": "e4e842f083515a8895442ae7d5ada5df",
            "figure": "https://i.imgur.com/IEzADyX.webp"
        },
        {
            "systematics": "klook",
            "title": "\u5531 \u6211\u5011\u7684\u6b4c \u6d41\u884c\u97f3\u6a02\u6545\u4e8b\u5c55 - \u9580\u7968",
            "date": "4\u67082\u65e5(\u9031\u4e8c) - 9\u670827\u65e5(\u9031\u4e94)",
            "address": "\u81fa\u5317\u6d41\u884c\u97f3\u6a02\u4e2d\u5fc3",
            "source_url": "https://www.klook.com/zh-TW/activity/70429-music-island-stories-pop-music-in-taiwan-taipei/",
            "UUID": "dde6739eefe25fe9aae6270e758d7acd",
            "figure": "https://i.imgur.com/3q0DDno.webp"
        }
    ],
    "visit": {}
}