{
    "information": {
        "fullname": "\u53f0\u5317\u6d41\u884c\u97f3\u6a02\u4e2d\u5fc3",
        "code_name": "tmc",
        "external_link": "https://tmc.taipei/show/event/"
    },
    "counts": 9,
    "last_update": "2023-03-29T17:38:17.433275+00:00",
    "data": [
        {
            "systematics": "tmc",
            "title": "\u81fa\u5317\u6d41\u884c\u97f3\u6a02\u4e2d\u5fc3\u3010\u5531 \u6211\u5011\u7684\u6b4c \u6d41\u884c\u97f3\u6a02\u6545\u4e8b\u5c55 MUSIC, ISLAND, STORIES: Pop Music in Taiwan\u3011",
            "date": "2021.09.18(\u516d)",
            "address": "\u6587\u5316\u9928",
            "source_url": "https://tmc.taipei/blog/show/music-island-stories/",
            "UUID": "5506d1dbc4f8592c8c731077ae2ee3ff",
            "figure": "https://i.imgur.com/dbtOqUB.webp"
        },
        {
            "systematics": "tmc",
            "title": "\u3010\u5927\u563b\u54c8\u6642\u4ee3 2 \u7e3d\u51a0\u8ecd\u8cfd\u3011\uff1a BE THE CHAMP \u51a0\u8ecd\u734e\u8ecd",
            "date": "2023.04.08(\u516d)",
            "address": "\u8868\u6f14\u5ef3",
            "source_url": "https://tmc.taipei/blog/show/%e3%80%90big-hip-hop-era-2%e3%80%91be-the-champ/",
            "UUID": "896e6e959f5e5a5a9c5deef4a49f8284",
            "figure": "https://tmc.taipei/wp-content/uploads/2023/03/2023\u5927\u563b\u54c8\u6642\u4ee32\u7e3d\u51a0\u8ecd-\u5317\u6d411360x680px.jpg"
        },
        {
            "systematics": "tmc",
            "title": "Ozone\u3010One And Only\u3011\u53f0\u5317\u6f14\u5531\u6703",
            "date": "2023.04.15(\u516d) \u2014 2023.04.16(\u65e5)",
            "address": "\u8868\u6f14\u5ef3",
            "source_url": "https://tmc.taipei/blog/show/ozone%e3%80%90one-and-only%e3%80%91tmc-live/?session=3457",
            "UUID": "8c3f2eeb90ad5f1880492c82d62ab045",
            "figure": "https://tmc.taipei/wp-content/uploads/2023/02/Ozone\u53f0\u5317\u6f14\u5531\u6703_\u52a0\u5834.jpg"
        },
        {
            "systematics": "tmc",
            "title": "\u9ec3\u91d1\u6b72\u6708\u6f14\u5531\u6703",
            "date": "2023.04.22(\u516d) \u2014 2023.04.23(\u65e5)",
            "address": "\u8868\u6f14\u5ef3",
            "source_url": "https://tmc.taipei/blog/show/golden-age-concert/?session=3344",
            "UUID": "b24175ee7acd5d79835f415057c98b9e",
            "figure": "https://i.imgur.com/02UXjcL.webp"
        },
        {
            "systematics": "tmc",
            "title": "2023\u70cf\u514b\u862d\u806f\u5408\u82ad\u857e\u821e\u5718\u300a\u6230\u6642\u8f13\u6b4c\u300b",
            "date": "2023.04.29(\u516d) \u2014 2023.04.30(\u65e5)",
            "address": "\u8868\u6f14\u5ef3",
            "source_url": "https://tmc.taipei/blog/show/2023ukrainian-ballet-wartime-elegy/?session=3473",
            "UUID": "b782b5d7fe335b1c8c7c26c949cc064f",
            "figure": "https://tmc.taipei/wp-content/uploads/2023/03/2023030310343529491920x1080_300k.jpg"
        },
        {
            "systematics": "tmc",
            "title": "2023\u300a\u767e\u5473\u4eba\u751f\u300b\u767e\u8b8a\u5eb7\u5eb7\u5de1\u8ff4\u6f14\u5531\u6703",
            "date": "2023.06.03(\u516d)",
            "address": "\u8868\u6f14\u5ef3",
            "source_url": "https://tmc.taipei/blog/show/kangkangs-taste-of-life-live-2023/",
            "UUID": "caa0746b679f58c993e5239f2d5d1130",
            "figure": "https://i.imgur.com/VXYxs6k.webp"
        },
        {
            "systematics": "tmc",
            "title": "\u7406\u60f3\u6df7\u86cb2023\u3010\u5947\u7570\u9edeBESTRANGE\u3011\u6f14\u5531\u6703",
            "date": "2023.08.19(\u516d)",
            "address": "\u8868\u6f14\u5ef3",
            "source_url": "https://tmc.taipei/blog/show/bestards2023%e3%80%90bestrange%e3%80%91live/",
            "UUID": "fdb62a01b9f05263b3da6a55246d8389",
            "figure": "https://i.imgur.com/yWDKzA5.webp"
        },
        {
            "systematics": "tmc",
            "title": "STOMP\u7834\u9285\u721b\u9435",
            "date": "2023.09.15(\u4e94) \u2014 2023.09.17(\u65e5)",
            "address": "\u8868\u6f14\u5ef3",
            "source_url": "https://tmc.taipei/blog/show/stomp-brokeniron0209/?session=2553",
            "UUID": "981c2e467f0653488f1a3f9c5d269d32",
            "figure": "https://i.imgur.com/K7PjmCK.webp"
        },
        {
            "systematics": "tmc",
            "title": "\u300a\u6f22\u65af\u5b63\u9ed8\uff1a\u597d\u840a\u5862\u738b\u8005\u4e4b\u97f3\u300b",
            "date": "2023.09.28(\u56db) \u2014 2023.10.01(\u65e5)",
            "address": "\u8868\u6f14\u5ef3",
            "source_url": "https://tmc.taipei/blog/show/theworldofmanszimmer/?session=2035",
            "UUID": "0b3279e7f3d75756a48eee928fe2bcff",
            "figure": "https://tmc.taipei/wp-content/uploads/2021/10/1360x680.jpg"
        }
    ],
    "visit": {}
}