{
    "information": {
        "fullname": "\u53f0\u5317\u4e16\u8cbf\u4e2d\u5fc3",
        "code_name": "twtc",
        "external_link": "https://twtc.com.tw/exhibition?p=home"
    },
    "counts": 3,
    "last_update": "2024-02-13T00:47:32.555948+00:00",
    "data": [
        {
            "systematics": "twtc",
            "title": "\u53f0\u5317\u570b\u969b\u81ea\u884c\u8eca\u5c55\u89bd\u6703",
            "date": "03/06 ~ 03/09",
            "address": "\u5357\u6e2f\u5c55\u89bd\u99281\u9928\u5357\u6e2f\u5c55\u89bd\u99282\u9928",
            "source_url": "http://www.taipeicycle.com.tw",
            "UUID": "72a6325fb458569d9c47d352bc48d176",
            "figure": ""
        },
        {
            "systematics": "twtc",
            "title": "\u53f0\u7063\u570b\u969b\u904b\u52d5\u53ca\u5065\u8eab\u5c55(\u539f\u53f0\u5317\u570b\u969b\u9ad4\u80b2\u7528\u54c1\u5c55)",
            "date": "03/06 ~ 03/09",
            "address": "\u5357\u6e2f\u5c55\u89bd\u99282\u9928",
            "source_url": "http://www.taispo.com.tw",
            "UUID": "758557d18b715d359a5b3fa2b0dbd44f",
            "figure": ""
        },
        {
            "systematics": "twtc",
            "title": "\u53f0\u7063\u570b\u969b\u5de5\u5177\u6a5f\u5c55",
            "date": "03/27 ~ 03/31",
            "address": "\u5357\u6e2f\u5c55\u89bd\u99282\u9928",
            "source_url": "https://www.tmts.tw/zh-TW",
            "UUID": "85513cbfebaa5693b6fa90e0a25beaa6",
            "figure": ""
        }
    ],
    "visit": {}
}