{
    "information": {
        "fullname": "udn\u552e\u7968\u7db2",
        "code_name": "tickets_udnfunlife",
        "external_link": "https://tickets.udnfunlife.com/application/UTK01/UTK0101_.aspx/GET_PUSH_LIST"
    },
    "counts": 17,
    "last_update": "2023-04-12T16:13:54.008125+00:00",
    "data": [
        {
            "systematics": "tickets_udnfunlife",
            "title": "2023\u300a\u767e\u5473\u4eba\u751f\u300b\u767e\u8b8a\u5eb7\u5eb7\u5de1\u8ff4\u6f14\u5531\u6703",
            "date": "2023/05/27 ~ 2023/06/03",
            "address": "\u9ad8\u96c4\u6d41\u884c\u97f3\u6a02\u4e2d\u5fc3 \u6d77\u97f3\u9928,\u81fa\u5317\u6d41\u884c\u97f3\u6a02\u4e2d\u5fc3",
            "source_url": "https://tickets.udnfunlife.com/Application/UTK02/UTK0201_.aspx?PRODUCT_ID=P01MD1OS&kdid=featured",
            "UUID": "3379aff2a7e956fb82b28b412254d1d8",
            "figure": "https://imgs2.utiki.com.tw/Data/UTIKI_UDN//Images/UTK2401/P01MD1OS_Product.JPG?v=202304111042"
        },
        {
            "systematics": "tickets_udnfunlife",
            "title": "\u300a\u8fea\u58eb\u5c3c\u52d5\u756b\u5c55\u300b",
            "date": "2023/06/21 ~ 2023/10/11",
            "address": "\u570b\u7acb\u4e2d\u6b63\u7d00\u5ff5\u5802 1\u5c55\u5ef3",
            "source_url": "https://tickets.udnfunlife.com/Application/UTK02/UTK0201_.aspx?PRODUCT_ID=P03K55N4&kdid=featured",
            "UUID": "340e206802705bb49bc13aa63181e032",
            "figure": "https://imgs2.utiki.com.tw/Data/UTIKI_UDN//Images/UTK2401/P03K55N4_Product.JPG?v=202304121636"
        },
        {
            "systematics": "tickets_udnfunlife",
            "title": "\u300a\u8fea\u58eb\u5c3c\u52d5\u756b\u5c55\u300b\u5957\u7968\u7d44\u5408",
            "date": "2023/06/21 ~ 2023/10/11",
            "address": "\u570b\u7acb\u4e2d\u6b63\u7d00\u5ff5\u5802 1\u5c55\u5ef3",
            "source_url": "https://tickets.udnfunlife.com/Application/UTK02/UTK0201_.aspx?PRODUCT_ID=P03KKS5K&kdid=featured",
            "UUID": "2babcc1a5c7c5bdfb2b12cf5f9d1f9b3",
            "figure": "https://imgs2.utiki.com.tw/Data/UTIKI_UDN//Images/UTK2401/P03KKS5K_Product.JPG?v=202304101559"
        },
        {
            "systematics": "tickets_udnfunlife",
            "title": "\u70cf\u514b\u862d\u806f\u5408\u82ad\u857e\u821e\u5718\u300a\u6230\u6642\u8f13\u6b4c\u300b",
            "date": "2023/04/29 ~ 2023/04/30",
            "address": "\u81fa\u5317\u6d41\u884c\u97f3\u6a02\u4e2d\u5fc3 \u8868\u6f14\u5ef3",
            "source_url": "https://tickets.udnfunlife.com/Application/UTK02/UTK0201_.aspx?PRODUCT_ID=P02A275Z&kdid=featured",
            "UUID": "6a389083c9b251ff9c928589b0e94e8c",
            "figure": "https://imgs2.utiki.com.tw/Data/UTIKI_UDN//Images/UTK2401/P02A275Z_Product.JPG?v=202304111141"
        },
        {
            "systematics": "tickets_udnfunlife",
            "title": "\u5492\u8853\u8ff4\u6230\u5c55 \u9ad8\u96c4\u5834",
            "date": "2023/06/30 ~ 2023/10/10",
            "address": "\u9ad8\u96c4\u99c1\u4e8c\u85dd\u8853\u7279\u5340 \u5927\u52c7\u5340 P3\u5009\u5eab",
            "source_url": "https://tickets.udnfunlife.com/Application/UTK02/UTK0201_.aspx?PRODUCT_ID=P0365U7P&kdid=featured",
            "UUID": "b9ed0bb338d15b258def11d49eef8816",
            "figure": "https://imgs2.utiki.com.tw/Data/UTIKI_UDN//Images/UTK2401/P0365U7P_Product.JPG?v=202304092326"
        },
        {
            "systematics": "tickets_udnfunlife",
            "title": "\u5492\u8853\u8ff4\u6230\u5c55 \u9ad8\u96c4\u5834\u5957\u7968\u7d44\u5408",
            "date": "2023/06/30 ~ 2023/10/10",
            "address": "\u9ad8\u96c4\u99c1\u4e8c\u85dd\u8853\u7279\u5340 \u5927\u52c7\u5340 P3\u5009\u5eab",
            "source_url": "https://tickets.udnfunlife.com/Application/UTK02/UTK0201_.aspx?PRODUCT_ID=P040VQMU&kdid=featured",
            "UUID": "d69319b6413f5ca48b8dc21b3caee664",
            "figure": "https://imgs2.utiki.com.tw/Data/UTIKI_UDN//Images/UTK2401/P040VQMU_Product.JPG?v=202304091853"
        },
        {
            "systematics": "tickets_udnfunlife",
            "title": "\u827e\u745e\uff0e\u5361\u723e\u597d\u597d\u4e94\u91cd\u594f\u89aa\u5b50\u4e92\u52d5\u5c55\uff08\u53f0\u5317\u5834\uff09",
            "date": "2023/04/13 ~ 2023/05/14",
            "address": "SOGO\u767e\u8ca8\u5fe0\u5b5d\u9928 12F\u6d3b\u52d5\u6703\u9928",
            "source_url": "https://tickets.udnfunlife.com/Application/UTK02/UTK0201_.aspx?PRODUCT_ID=P03TDF93&kdid=featured",
            "UUID": "1965065698385df18ecc58dd998d83f8",
            "figure": "https://imgs2.utiki.com.tw/Data/UTIKI_UDN//Images/UTK2401/P03TDF93_Product.JPG?v=202303101759"
        },
        {
            "systematics": "tickets_udnfunlife",
            "title": "\u6f22\u65af\u5b63\u9ed8\uff1a\u597d\u840a\u5862\u738b\u8005\u4e4b\u97f3",
            "date": "2023/09/28 ~ 2023/10/01",
            "address": "\u81fa\u5317\u5c0f\u5de8\u86cb,\u81fa\u5317\u6d41\u884c\u97f3\u6a02\u4e2d\u5fc3",
            "source_url": "https://tickets.udnfunlife.com/Application/UTK02/UTK0201_.aspx?PRODUCT_ID=N0BAK22N&kdid=featured",
            "UUID": "e0784940b0cd516a99112a9b69c238c8",
            "figure": "https://i.imgur.com/ApslVEQ.webp"
        },
        {
            "systematics": "tickets_udnfunlife",
            "title": "\u5531 \u6211\u5011\u7684\u6b4c \u6d41\u884c\u97f3\u6a02\u6545\u4e8b\u5c55",
            "date": "2022/09/01 ~ 2023/12/31",
            "address": "\u81fa\u5317\u6d41\u884c\u97f3\u6a02\u4e2d\u5fc3 \u6587\u5316\u9928 4~6\u6a13",
            "source_url": "https://tickets.udnfunlife.com/Application/UTK02/UTK0201_.aspx?PRODUCT_ID=N23SE92T&kdid=featured",
            "UUID": "3050b601e161530ea819b75dccf95d20",
            "figure": "https://imgs2.utiki.com.tw/Data/UTIKI_UDN//Images/UTK2401/N23SE92T_Product.JPG?v=202303291510"
        },
        {
            "systematics": "tickets_udnfunlife",
            "title": "\u4e16\u754c\u767e\u5927\u540d\u756b\u5927\u5c55",
            "date": "2022/10/20 ~ 2023/05/14",
            "address": "\u7fa9\u4eab\u6642\u5c1a\u5ee3\u5834 1\u6a13",
            "source_url": "https://tickets.udnfunlife.com/Application/UTK02/UTK0201_.aspx?PRODUCT_ID=N27Q0Q76&kdid=featured",
            "UUID": "7b451352b6c95aecbf90958143b0b228",
            "figure": "https://imgs2.utiki.com.tw/Data/UTIKI_UDN//Images/UTK2401/N27Q0Q76_Product.JPG?v=202303011726"
        },
        {
            "systematics": "tickets_udnfunlife",
            "title": "2023\u6703\u6f14\u662f\u82f1\u96c4",
            "date": "2023/04/22 ~ 2023/04/23",
            "address": "\u570b\u5bb6\u6232\u5287\u9662,\u81fa\u4e2d\u5e02\u5c6f\u5340\u85dd\u6587\u4e2d\u5fc3,\u885b\u6b66\u71df\u570b\u5bb6\u85dd\u8853\u6587\u5316\u4e2d\u5fc3 \u6232\u5287\u9662",
            "source_url": "https://tickets.udnfunlife.com/Application/UTK02/UTK0201_.aspx?PRODUCT_ID=N2888FU9&kdid=featured",
            "UUID": "0c66aaf6b56b578592b171a779cacbc3",
            "figure": "https://imgs2.utiki.com.tw/Data/UTIKI_UDN//Images/UTK2401/N2888FU9_Product.JPG?v=202303230956"
        },
        {
            "systematics": "tickets_udnfunlife",
            "title": "\u300a\u9280\u8272\u751f\u6b7b\u6200\u300b",
            "date": "2023/04/28 ~ 2023/04/30",
            "address": "PLAYground \u5357\u6751\u5287\u5834",
            "source_url": "https://tickets.udnfunlife.com/Application/UTK02/UTK0201_.aspx?PRODUCT_ID=P02HSZ03&kdid=featured",
            "UUID": "aaacf7ef27885e28beb2e99d408d61bc",
            "figure": "https://imgs2.utiki.com.tw/Data/UTIKI_UDN//Images/UTK2401/P02HSZ03_Product.JPG?v=202302211155"
        },
        {
            "systematics": "tickets_udnfunlife",
            "title": "2023\u53f0\u5317\u570b\u969b\u9152\u5c55\u2027\u7d14\u9152\u5c55",
            "date": "2023/04/14 ~ 2023/04/17",
            "address": "\u53f0\u5317\u4e16\u754c\u8cbf\u6613\u4e2d\u5fc3 \u5c55\u89bd\u4e00\u9928",
            "source_url": "https://tickets.udnfunlife.com/Application/UTK02/UTK0201_.aspx?PRODUCT_ID=P03G33NT&kdid=featured",
            "UUID": "56ae97270f5452bfbee44907db600c0d",
            "figure": "https://imgs2.utiki.com.tw/Data/UTIKI_UDN//Images/UTK2401/P03G33NT_Product.JPG?v=202303071157"
        },
        {
            "systematics": "tickets_udnfunlife",
            "title": "\u83ef\u71c8\u521d\u4e0a \u6c89\u6d78\u5f0f\u5287\u5834",
            "date": "2023/04/14 ~ 2023/05/28",
            "address": "\u5167\u6e56\u6607\u6046\u660c\u65d7\u8266\u5e97",
            "source_url": "https://tickets.udnfunlife.com/Application/UTK02/UTK0201_.aspx?PRODUCT_ID=P0426Z44&kdid=featured",
            "UUID": "a398c7afdf3155389f2aabbda3b414a1",
            "figure": "https://imgs2.utiki.com.tw/Data/UTIKI_UDN//Images/UTK2401/P0426Z44_Product.PNG?v=202303301541"
        },
        {
            "systematics": "tickets_udnfunlife",
            "title": "\u300a\u547d\u904b\u4e4b\u7d04\u300b",
            "date": "2023/04/14 ~ 2023/04/15",
            "address": "PLAYground \u5357\u6751\u5287\u5834",
            "source_url": "https://tickets.udnfunlife.com/Application/UTK02/UTK0201_.aspx?PRODUCT_ID=P02HG4T2&kdid=featured",
            "UUID": "0bf4784051ec5537b71e785d3acf2053",
            "figure": "https://imgs2.utiki.com.tw/Data/UTIKI_UDN//Images/UTK2401/P02HG4T2_Product.JPG?v=202303151800"
        },
        {
            "systematics": "tickets_udnfunlife",
            "title": "\u300a\u6211\u5abd\u8aaa\u6211\u501f\u4f86\u7684\u547d\u53ea\u80fd\u7528\u5230\u4e8c\u5341\u4e5d\u300b",
            "date": "2023/06/23 ~ 2023/06/25",
            "address": "PLAYground \u5357\u6751\u5287\u5834",
            "source_url": "https://tickets.udnfunlife.com/Application/UTK02/UTK0201_.aspx?PRODUCT_ID=P03TDF8D&kdid=featured",
            "UUID": "bacfb76281875fd4871a5db309a2eb27",
            "figure": "https://imgs2.utiki.com.tw/Data/UTIKI_UDN//Images/UTK2401/P03TDF8D_Product.JPG?v=202303151818"
        },
        {
            "systematics": "tickets_udnfunlife",
            "title": "\u611b\u624b\u5275\u65e5\u672c\u624b\u4f5c\u796d \u7b2c\u4e94\u56de",
            "date": "2023/06/09 ~ 2023/06/11",
            "address": "\u83ef\u5c711914\u6587\u5316\u5275\u610f\u7522\u696d\u5712\u5340 \u6771\u4e8c\u9928\u56db\u9023\u68df",
            "source_url": "https://tickets.udnfunlife.com/Application/UTK02/UTK0201_.aspx?PRODUCT_ID=P03Z76K3&kdid=featured",
            "UUID": "12fbaf9525ce5406ab02228649af5459",
            "figure": "https://imgs2.utiki.com.tw/Data/UTIKI_UDN//Images/UTK2401/P03Z76K3_Product.JPG?v=202303281641"
        }
    ],
    "visit": {}
}